{
	"teamMembers": [
		{
			"gender": "male",
			"name": {
				"title": "mr",
				"first": "jordan",
				"last": "rogers"
			},
			"location": {
				"street": "7410 w pecan st",
				"city": "cairns",
				"state": "victoria",
				"postcode": 8779
			},
			"email": "jordan.rogers@example.com",
			"login": {
				"username": "yellowgorilla223",
				"password": "cheese",
				"salt": "DFDGOgyN",
				"md5": "88e9384860accb788046951ceb8e7b78",
				"sha1": "7a6934b8cc56ed9ad297db101a692304bf95a8bd",
				"sha256": "feb02b55397efab147b81375cb3c983298444b0d2902e0e4f27684a60ddca798"
			},
			"dob": "1971-03-21 03:29:38",
			"registered": "2014-10-05 20:56:52",
			"phone": "09-7080-7540",
			"cell": "0488-236-632",
			"id": {
				"name": "TFN",
				"value": "899000233"
			},
			"picture": {
				"large": "https://randomuser.me/api/portraits/men/86.jpg",
				"medium": "https://randomuser.me/api/portraits/med/men/86.jpg",
				"thumbnail": "https://randomuser.me/api/portraits/thumb/men/86.jpg"
			},
			"nat": "AU"
		},
		{
			"gender": "female",
			"name": {
				"title": "miss",
				"first": "sofia",
				"last": "muñoz"
			},
			"location": {
				"street": "3615 calle del prado",
				"city": "ferrol",
				"state": "extremadura",
				"postcode": 16751
			},
			"email": "sofia.muñoz@example.com",
			"login": {
				"username": "purpleswan459",
				"password": "zuan",
				"salt": "fNIhlw75",
				"md5": "d57f014a08bcef6ee3d960212a114e2f",
				"sha1": "4dd86be1fc2a71105b9fc2754473aa0d29ef236c",
				"sha256": "61e6beeaa2a49702c2fd6744e833e7c18efda1819c3ee23c335096c109633089"
			},
			"dob": "1984-07-30 15:10:17",
			"registered": "2016-03-31 09:21:15",
			"phone": "906-875-561",
			"cell": "636-708-583",
			"id": {
				"name": "DNI",
				"value": "05674475-Z"
			},
			"picture": {
				"large": "https://randomuser.me/api/portraits/women/15.jpg",
				"medium": "https://randomuser.me/api/portraits/med/women/15.jpg",
				"thumbnail": "https://randomuser.me/api/portraits/thumb/women/15.jpg"
			},
			"nat": "ES"
		},
		{
			"gender": "female",
			"name": {
				"title": "ms",
				"first": "marie",
				"last": "madsen"
			},
			"location": {
				"street": "3592 damgårdsvej",
				"city": "jystrup",
				"state": "sjælland",
				"postcode": 51821
			},
			"email": "marie.madsen@example.com",
			"login": {
				"username": "heavypanda207",
				"password": "generic",
				"salt": "jfysYeUT",
				"md5": "b6dfcd29025c66f8d50e3030d5199d6f",
				"sha1": "3a00970871668000a18fbbb0cc9d7746bf05c556",
				"sha256": "5a16088523c2ff51e8307f3ee4ecae2bb011c8d1ddf23f6a9fbb1b0cceb8a28b"
			},
			"dob": "1976-09-10 22:22:43",
			"registered": "2008-12-21 13:39:51",
			"phone": "24659623",
			"cell": "92513293",
			"id": {
				"name": "CPR",
				"value": "749524-4065"
			},
			"picture": {
				"large": "https://randomuser.me/api/portraits/women/43.jpg",
				"medium": "https://randomuser.me/api/portraits/med/women/43.jpg",
				"thumbnail": "https://randomuser.me/api/portraits/thumb/women/43.jpg"
			},
			"nat": "DK"
		},
		{
			"gender": "male",
			"name": {
				"title": "mr",
				"first": "walter",
				"last": "henry"
			},
			"location": {
				"street": "4033 mill road",
				"city": "portarlington",
				"state": "westmeath",
				"postcode": 30550
			},
			"email": "walter.henry@example.com",
			"login": {
				"username": "lazyduck353",
				"password": "luther",
				"salt": "gndbadNJ",
				"md5": "2cb8aa03ed1198369342bd177ee0083c",
				"sha1": "ad0da00cf3d1b3c4ad89a5d22ab24fc50847030d",
				"sha256": "c4e0190db10d6bf7ea7cf34e30710b72dc71bbdc8698531f00d476c05fb4393d"
			},
			"dob": "1976-03-16 16:30:03",
			"registered": "2008-07-17 08:25:41",
			"phone": "021-518-5683",
			"cell": "081-371-4628",
			"id": {
				"name": "PPS",
				"value": "3755548T"
			},
			"picture": {
				"large": "https://randomuser.me/api/portraits/men/88.jpg",
				"medium": "https://randomuser.me/api/portraits/med/men/88.jpg",
				"thumbnail": "https://randomuser.me/api/portraits/thumb/men/88.jpg"
			},
			"nat": "IE"
		},
		{
			"gender": "male",
			"name": {
				"title": "mr",
				"first": "armando",
				"last": "lord"
			},
			"location": {
				"street": "1696 the grove",
				"city": "londonderry",
				"state": "central",
				"postcode": "I6G 8WZ"
			},
			"email": "armando.lord@example.com",
			"login": {
				"username": "heavypanda268",
				"password": "dogface",
				"salt": "QOOnJOKN",
				"md5": "b52bde614654c0ee02e63abf3e722000",
				"sha1": "fe2eb933e8311a93e47bfd8861dafdb96d73198c",
				"sha256": "3ffb0f18168ebcd01707e25f03642d011c4a23ddb4640ab3aed13335b7c28eec"
			},
			"dob": "1982-08-04 20:46:47",
			"registered": "2015-12-15 04:42:55",
			"phone": "017684 89800",
			"cell": "0761-105-262",
			"id": {
				"name": "NINO",
				"value": "AW 71 87 55 T"
			},
			"picture": {
				"large": "https://randomuser.me/api/portraits/men/33.jpg",
				"medium": "https://randomuser.me/api/portraits/med/men/33.jpg",
				"thumbnail": "https://randomuser.me/api/portraits/thumb/men/33.jpg"
			},
			"nat": "GB"
		},
		{
			"gender": "female",
			"name": {
				"title": "miss",
				"first": "leire",
				"last": "da paz"
			},
			"location": {
				"street": "4150 rua josé bonifácio ",
				"city": "alagoinhas",
				"state": "sergipe",
				"postcode": 61991
			},
			"email": "leire.dapaz@example.com",
			"login": {
				"username": "beautifulbear279",
				"password": "woody",
				"salt": "li8GeKAB",
				"md5": "7b9f8011f7b3e28fa850324d9e8e85fa",
				"sha1": "9c4776e0c03317e5ec60ad1c66b496047bca1bb2",
				"sha256": "0da0af475341fc7ef71f032d856d45edf0b00358beebaf821173eeb3281e3913"
			},
			"dob": "1984-02-13 20:15:11",
			"registered": "2011-07-10 08:29:32",
			"phone": "(59) 7884-2622",
			"cell": "(94) 2668-7739",
			"id": {
				"name": "",
				"value": null
			},
			"picture": {
				"large": "https://randomuser.me/api/portraits/women/52.jpg",
				"medium": "https://randomuser.me/api/portraits/med/women/52.jpg",
				"thumbnail": "https://randomuser.me/api/portraits/thumb/women/52.jpg"
			},
			"nat": "BR"
		},
		{
			"gender": "male",
			"name": {
				"title": "mr",
				"first": "paul",
				"last": "morris"
			},
			"location": {
				"street": "9640 samaritan dr",
				"city": "broken arrow",
				"state": "illinois",
				"postcode": 84865
			},
			"email": "paul.morris@example.com",
			"login": {
				"username": "brownmouse630",
				"password": "buzzard",
				"salt": "HSQYHTPp",
				"md5": "5fa0d6efea9f7c8ed9365504b30672cb",
				"sha1": "97cc3a84bc8dc2c4e7f88c76792ad381d5198daf",
				"sha256": "7ffb7e65986c6bd776202016bd3c51c6be49a4a2045eb631e149077822b5269c"
			},
			"dob": "1983-06-02 02:50:15",
			"registered": "2005-11-29 23:32:06",
			"phone": "(109)-292-4411",
			"cell": "(350)-379-8123",
			"id": {
				"name": "SSN",
				"value": "125-75-2161"
			},
			"picture": {
				"large": "https://randomuser.me/api/portraits/men/30.jpg",
				"medium": "https://randomuser.me/api/portraits/med/men/30.jpg",
				"thumbnail": "https://randomuser.me/api/portraits/thumb/men/30.jpg"
			},
			"nat": "US"
		},
		{
			"gender": "female",
			"name": {
				"title": "mrs",
				"first": "mattie",
				"last": "ward"
			},
			"location": {
				"street": "8588 lakeshore rd",
				"city": "bathurst",
				"state": "queensland",
				"postcode": 5611
			},
			"email": "mattie.ward@example.com",
			"login": {
				"username": "crazyswan974",
				"password": "henry",
				"salt": "KagCBH1R",
				"md5": "f5c45f9d2528f5044ac872a27c39655f",
				"sha1": "197bcbf353b4a94367e3ed325d9aa3a9a77a9818",
				"sha256": "3b2023ac5e92438bea51d29913c9d1b99d4ac0ea88b3aa02a4d873f0e70662c2"
			},
			"dob": "1990-03-15 08:17:22",
			"registered": "2004-09-06 07:56:03",
			"phone": "01-6327-2448",
			"cell": "0491-434-255",
			"id": {
				"name": "TFN",
				"value": "751710902"
			},
			"picture": {
				"large": "https://randomuser.me/api/portraits/women/42.jpg",
				"medium": "https://randomuser.me/api/portraits/med/women/42.jpg",
				"thumbnail": "https://randomuser.me/api/portraits/thumb/women/42.jpg"
			},
			"nat": "AU"
		},
		{
			"gender": "female",
			"name": {
				"title": "mrs",
				"first": "méline",
				"last": "bernard"
			},
			"location": {
				"street": "6510 rue du moulin",
				"city": "le havre",
				"state": "loiret",
				"postcode": 71839
			},
			"email": "méline.bernard@example.com",
			"login": {
				"username": "smalllion786",
				"password": "moore",
				"salt": "Bikfm8Mh",
				"md5": "7c7ae8e14eeb4c3a321ab588a981f5e4",
				"sha1": "db0d33950b13bd957967062a8168a4436496d417",
				"sha256": "04551f29646cd0b1a5472bfa796cf1909a934e872fa5ecc6a9ca4267aa61d85c"
			},
			"dob": "1944-11-08 23:12:59",
			"registered": "2009-08-26 15:33:33",
			"phone": "03-35-87-13-60",
			"cell": "06-00-57-87-43",
			"id": {
				"name": "INSEE",
				"value": "2441044925959 43"
			},
			"picture": {
				"large": "https://randomuser.me/api/portraits/women/58.jpg",
				"medium": "https://randomuser.me/api/portraits/med/women/58.jpg",
				"thumbnail": "https://randomuser.me/api/portraits/thumb/women/58.jpg"
			},
			"nat": "FR"
		},
		{
			"gender": "female",
			"name": {
				"title": "miss",
				"first": "susan",
				"last": "otoole"
			},
			"location": {
				"street": "5665 park road",
				"city": "birr",
				"state": "westmeath",
				"postcode": 90208
			},
			"email": "susan.otoole@example.com",
			"login": {
				"username": "organicmeercat888",
				"password": "slapshot",
				"salt": "ce16uPSR",
				"md5": "e70d890928f5a8ca7b601fe456701cf6",
				"sha1": "6b3a2b50555afa5f6af7025c3c66b926814fb46c",
				"sha256": "78920d2dc1e94e991758efc7346cab4c8f123a44d99623d3cb94651fd637f3f5"
			},
			"dob": "1974-08-29 19:26:42",
			"registered": "2012-11-29 10:02:07",
			"phone": "071-342-4493",
			"cell": "081-127-7134",
			"id": {
				"name": "PPS",
				"value": "2093945T"
			},
			"picture": {
				"large": "https://randomuser.me/api/portraits/women/33.jpg",
				"medium": "https://randomuser.me/api/portraits/med/women/33.jpg",
				"thumbnail": "https://randomuser.me/api/portraits/thumb/women/33.jpg"
			},
			"nat": "IE"
		}
	],
	"info": {
		"seed": "131ccdeeeaec54e4",
		"results": 10,
		"page": 1,
		"version": "1.1"
	}
}